test_proj/__init__.py
test_proj/main.py
test_proj/test.py
testhist-1.1.0.dist-info/METADATA
testhist-1.1.0.dist-info/WHEEL
testhist-1.1.0.dist-info/top_level.txt
testhist-1.1.0.dist-info/RECORD
